ynab/__init__.py
ynab/api_client.py
ynab/api_response.py
ynab/configuration.py
ynab/exceptions.py
ynab/py.typed
ynab/rest.py
ynab/api/__init__.py
ynab/api/accounts_api.py
ynab/api/budgets_api.py
ynab/api/categories_api.py
ynab/api/months_api.py
ynab/api/payee_locations_api.py
ynab/api/payees_api.py
ynab/api/scheduled_transactions_api.py
ynab/api/transactions_api.py
ynab/api/user_api.py
ynab/models/__init__.py
ynab/models/account.py
ynab/models/account_response.py
ynab/models/account_response_data.py
ynab/models/account_type.py
ynab/models/accounts_response.py
ynab/models/accounts_response_data.py
ynab/models/budget_detail.py
ynab/models/budget_detail_response.py
ynab/models/budget_detail_response_data.py
ynab/models/budget_settings.py
ynab/models/budget_settings_response.py
ynab/models/budget_settings_response_data.py
ynab/models/budget_summary.py
ynab/models/budget_summary_response.py
ynab/models/budget_summary_response_data.py
ynab/models/bulk_response.py
ynab/models/bulk_response_data.py
ynab/models/bulk_response_data_bulk.py
ynab/models/bulk_transactions.py
ynab/models/categories_response.py
ynab/models/categories_response_data.py
ynab/models/category.py
ynab/models/category_group.py
ynab/models/category_group_with_categories.py
ynab/models/category_response.py
ynab/models/category_response_data.py
ynab/models/currency_format.py
ynab/models/date_format.py
ynab/models/error_detail.py
ynab/models/error_response.py
ynab/models/existing_transaction.py
ynab/models/hybrid_transaction.py
ynab/models/hybrid_transactions_response.py
ynab/models/hybrid_transactions_response_data.py
ynab/models/month_detail.py
ynab/models/month_detail_response.py
ynab/models/month_detail_response_data.py
ynab/models/month_summaries_response.py
ynab/models/month_summaries_response_data.py
ynab/models/month_summary.py
ynab/models/new_transaction.py
ynab/models/patch_category_wrapper.py
ynab/models/patch_month_category_wrapper.py
ynab/models/patch_transactions_wrapper.py
ynab/models/payee.py
pyynab-0.10.1.dist-info/METADATA
pyynab-0.10.1.dist-info/WHEEL
pyynab-0.10.1.dist-info/top_level.txt
pyynab-0.10.1.dist-info/RECORD
