Metadata-Version: 2.1
Name: pyynab
Version: 0.10.1
Summary: YNAB API Endpoints
Home-page: 
Author: OpenAPI Generator community
Author-email: cheery.iron6016@fastmail.com
Keywords: OpenAPI,OpenAPI-Generator,YNAB API Endpoints
Requires-Dist: urllib3 <2.1.0,>=1.25.3
Requires-Dist: python-dateutil
Requires-Dist: pydantic >=2
Requires-Dist: typing-extensions >=4.7.1
